lc_correction/__init__.py
lc_correction/compute.py
lc_correction/helpers.py
lc_correction-1.0.0.dist-info/LICENSE
lc_correction-1.0.0.dist-info/METADATA
lc_correction-1.0.0.dist-info/WHEEL
lc_correction-1.0.0.dist-info/top_level.txt
lc_correction-1.0.0.dist-info/RECORD
